files2db/__init__.py
files2db/databases.py
files2db/main.py
src/databases.py
src/main.py
files2db-0.1.1.dist-info/LICENSE
files2db-0.1.1.dist-info/METADATA
files2db-0.1.1.dist-info/WHEEL
files2db-0.1.1.dist-info/entry_points.txt
files2db-0.1.1.dist-info/top_level.txt
files2db-0.1.1.dist-info/RECORD
