Metadata-Version: 2.1
Name: files2db
Version: 0.1.1
Summary: Migration from local files to database made simple!
Home-page: https://github.com/FluffyDietEngine/files-2-db
Author: Santhosh Solomon
Author-email: solomon.santhosh@gmail.com
License: Apache License 2.0
Keywords: data-migration,mysql,csv,data-engineering,automation
Platform: any
Classifier: Operating System :: OS Independent
Classifier: Programming Language :: Python
Classifier: Programming Language :: Python :: 3
Classifier: License :: OSI Approved :: Apache Software License
Classifier: Intended Audience :: Developers
License-File: LICENSE
Requires-Dist: polars ==0.20.6
Requires-Dist: PyMySQL ==1.1.0
